eqassertions/__init__.py
eqassertions-0.4.dist-info/LICENSE
eqassertions-0.4.dist-info/METADATA
eqassertions-0.4.dist-info/WHEEL
eqassertions-0.4.dist-info/top_level.txt
eqassertions-0.4.dist-info/RECORD
