Metadata-Version: 2.1
Name: eqassertions
Version: 0.4
Summary: assertions in __eq__methods
Home-page: https://github.com/aodag/eqassertions
Author: Atsushi Odagiri
Author-email: aodagx@gmail.com
License: MIT
Platform: UNKNOWN
Provides-Extra: testing
Provides-Extra: dev
